{
    "tags": [
        "collection"
    ],
    "contained_entries": {
        "shell": "shell",
        "git": "git",
        "base_map": "base_map",
        "derived_map": "derived_map",
        "be_like": "be_like",
        "dont_be_like": "dont_be_like",
        "downloader": "downloader",
        "sysinfo": "sysinfo",
        "pip": "pip",
        "base_pip_package": "base_pip_package",
        "numpy_import_test": "numpy_import_test",
        "python_script": "python_script",
        "pytorch_image_classifier": "pytorch_image_classifier",
        "tool_detector": "tool_detector",
        "extractor": "extractor",
        "imagenet500_recipe": "imagenet500_recipe",
        "imagenet_annotation_recipe": "imagenet_annotation_recipe",
        "pillow_process_imagenet": "pillow_process_imagenet",
        "rule_matching_demonstrator": "rule_matching_demonstrator",
        "model_onnx_resnet50_recipe": "model_onnx_resnet50_recipe",
        "onnx_image_classifier": "onnx_image_classifier",
        "model_onnx_mobilenet_recipe": "model_onnx_mobilenet_recipe",
        "base_imagenet_experiment": "base_imagenet_experiment",
        "model_tf_mobilenet_v2_recipe": "model_tf_mobilenet_v2_recipe",
        "tf_image_classifier": "tf_image_classifier",
        "model_onnx_ssd_resnet34_recipe": "model_onnx_ssd_resnet34_recipe",
        "coco_annotation_recipe": "coco_annotation_recipe",
        "coco_images_recipe": "coco_images_recipe",
        "pillow_resize_for_object_detection": "pillow_resize_for_object_detection",
        "onnx_object_detector": "onnx_object_detector",
        "base_coco_experiment": "base_coco_experiment",
        "mlperf_inference_git_recipe": "mlperf_inference_git_recipe",
        "loadgen_example": "loadgen_example",
        "loadgen_wheel_recipe": "loadgen_wheel_recipe",
        "image_classification_torch_loadgen_py": "image_classification_torch_loadgen_py",
        "base_imagenet_loadgen_experiment": "base_imagenet_loadgen_experiment",
        "imagenet_preprocessed_loader": "imagenet_preprocessed_loader",
        "coco_preprocessed_loader": "coco_preprocessed_loader",
        "image_classification_onnx_loadgen_py": "image_classification_onnx_loadgen_py",
        "object_detection_onnx_loadgen_py": "object_detection_onnx_loadgen_py",
        "base_object_detection_loadgen_experiment": "base_object_detection_loadgen_experiment",
        "model_onnx_retinanet_coco_recipe": "model_onnx_retinanet_coco_recipe",
        "chai_sut": "chai_sut",
        "python_in_shell": "python_in_shell",
        "model_onnx_retinanet_openimages_recipe": "model_onnx_retinanet_openimages_recipe",
        "openimages_mlperf_recipe": "openimages_mlperf_recipe",
        "base_loadgen_experiment": "base_loadgen_experiment"
    }
}
